inventree_rapidoc/RapidocPlugin.py
inventree_rapidoc/__init__.py
inventree_rapidoc-1.2.dist-info/METADATA
inventree_rapidoc-1.2.dist-info/WHEEL
inventree_rapidoc-1.2.dist-info/entry_points.txt
inventree_rapidoc-1.2.dist-info/top_level.txt
inventree_rapidoc-1.2.dist-info/RECORD
